hat/peg.py
hat_peg-0.5.10.dist-info/LICENSE
hat_peg-0.5.10.dist-info/METADATA
hat_peg-0.5.10.dist-info/WHEEL
hat_peg-0.5.10.dist-info/RECORD
