Metadata-Version: 2.1
Name: hat-peg
Version: 0.5.10
Summary: Hat PEG parser
License: Apache-2.0
Classifier: Programming Language :: Python :: 3
Classifier: License :: OSI Approved :: Apache Software License
Provides-Extra: dev
Requires-Dist: hat-util ~=0.6.16
Requires-Dist: hat-doit ~=0.15.18; extra == 'dev'
Requires-Python: >=3.10
Project-URL: Homepage, http://hat-open.com
Project-URL: Repository, https://github.com/hat-open/hat-peg.git
Project-URL: Documentation, http://hat-peg.hat-open.com
